whr_core.cp314-win_amd64.pyd
whr/__init__.py
whr/base.py
whr/evaluate.py
whr-2.1.0.dist-info/licenses/LICENSE
whr-2.1.0.dist-info/METADATA
whr-2.1.0.dist-info/WHEEL
whr-2.1.0.dist-info/top_level.txt
whr-2.1.0.dist-info/RECORD
