Metadata-Version: 2.4
Name: whr
Version: 2.1.0
Summary: A Python interface incorporating a C++ implementation of the Whole History Rating algorithm proposed by Rémi Coulom. The implementation is based on the Ruby code of GoShrine.
Home-page: https://github.com/wind23/whole_history_rating/
Download-URL: https://github.com/wind23/whole_history_rating/archive/2.1.0.tar.gz
Author: Tianyi Hao, Pete Schwamb
Author-email: haotianyi0@126.com
License: MIT
Keywords: WHR,whole history rating,Elo rating
Classifier: Development Status :: 5 - Production/Stable
Classifier: Intended Audience :: Developers
Classifier: License :: OSI Approved :: MIT License
Classifier: Programming Language :: Python :: 3
Requires-Python: >=3.6
License-File: LICENSE
Provides-Extra: test
Requires-Dist: pytest; extra == "test"
Dynamic: author
Dynamic: author-email
Dynamic: classifier
Dynamic: description
Dynamic: description-content-type
Dynamic: download-url
Dynamic: home-page
Dynamic: keywords
Dynamic: license
Dynamic: license-file
Dynamic: provides-extra
Dynamic: requires-python
Dynamic: summary
